emosent/__init__.py
emosent/emosent.py
emosent/data/Emoji_Sentiment_Data_v1.0.csv
emosent_py-0.1.7.dist-info/LICENSE.txt
emosent_py-0.1.7.dist-info/METADATA
emosent_py-0.1.7.dist-info/WHEEL
emosent_py-0.1.7.dist-info/top_level.txt
emosent_py-0.1.7.dist-info/RECORD
