Metadata-Version: 2.1
Name: emosent-py
Version: 0.1.7
Summary: Python module to get Sentiment Rankings for Unicode Emojis.
Home-page: https://github.com/omkar-foss/emosent-py
Download-URL: https://github.com/FintelLabs/emosent-py/archive/master.zip
Author: Omkar P
License: MIT
Keywords: emoji,sentiment,analysis,ranking,emoticon,polarity
Classifier: Development Status :: 4 - Beta
Classifier: Intended Audience :: Developers
Classifier: Topic :: Software Development :: Build Tools
Classifier: License :: OSI Approved :: MIT License
Classifier: Programming Language :: Python :: 3
Classifier: Programming Language :: Python :: 3.4
Classifier: Programming Language :: Python :: 3.5
Classifier: Programming Language :: Python :: 3.6
Classifier: Programming Language :: Python :: 3.7
Classifier: Programming Language :: Python :: 3.8
Classifier: Programming Language :: Python :: 3.9
Classifier: Programming Language :: Python :: 3.10
License-File: LICENSE.txt
